pimodules/__init__.py
pimodules/alerts.py
pimodules/configuration.py
pimodules/daemon.py
pimodules-0.1.dist-info/LICENSE
pimodules-0.1.dist-info/METADATA
pimodules-0.1.dist-info/WHEEL
pimodules-0.1.dist-info/top_level.txt
pimodules-0.1.dist-info/RECORD
